{
  "$schema": "../node_modules/@tauri-apps/cli/config.schema.json",
  "productName": "Power Paste",
  "version": "0.4.0",
  "identifier": "com.yulei.powerpaste",
  "build": {
    "frontendDist": "../dist",
    "devUrl": "http://localhost:5173",
    "beforeDevCommand": "node scripts/tauri-dev-server.mjs",
    "beforeBuildCommand": "pnpm build"
  },
  "plugins": {
    "updater": {
      "pubkey": "dW50cnVzdGVkIGNvbW1lbnQ6IG1pbmlzaWduIHB1YmxpYyBrZXk6IDhGNkU5ODFENDVCRkRENDEKUldSQjNiOUZIWmh1ai8xNEdXdWkrTHFCRjZySUVKQ3VQdnRIWGNMWEoxR1psdDRoMUtFL2JPeEsK",
      "endpoints": [
        "https://github.com/iFence/power-paste/releases/latest/download/latest.json"
      ]
    }
  },
  "app": {
    "macOSPrivateApi": true,
    "windows": [
      {
        "label": "main",
        "title": "Power Paste",
        "width": 380,
        "height": 760,
        "minWidth": 380,
        "minHeight": 600,
        "decorations": false,
        "transparent": true,
        "devtools": false,
        "resizable": true,
        "visible": false,
        "center": true
      }
    ],
    "security": {
      "capabilities": ["default"],
      "csp": null
    }
  },
  "bundle": {
    "active": true,
    "createUpdaterArtifacts": true,
    "icon": [
      "icons/32x32.png",
      "icons/128x128.png",
      "icons/128x128@2x.png",
      "icons/icon.ico",
      "icons/icon.icns"
    ],
    "targets": "all",
    "windows": {
      "nsis": {
        "languages": ["SimpChinese"]
      },
      "wix": {
        "language": ["zh-CN"]
      }
    }
  }
}
